{
  "title": "Álvaro García's Hip Hop Tutorials",
  "author": "Álvaro García",
  "style": "hiphop",
  "language": "es",
  "thumbnail": "https://i.ytimg.com/vi/vbWziMUR5XU/mqdefault.jpg",
  "sections": [
    {
      "title": "Introducción",
      "videos": [
        {
          "youtubeId": "vbWziMUR5XU",
          "duration": "PT2M27S",
          "title": "Introducción",
          "height": 270,
          "width": 480
        },
        {
          "youtubeId": "gIVerlT0IRk",
          "duration": "PT1M58S",
          "title": "Desplazamientos",
          "height": 270,
          "width": 480
        }
      ]
    },
    {
      "title": "Steps - 1",
      "videos": [
        {
          "youtubeId": "g8PI_qgadhA",
          "duration": "PT1M25S",
          "title": "Running man",
          "height": 270,
          "width": 480
        },
        {
          "youtubeId": "bFJLPd-wowk",
          "duration": "PT1M26S",
          "title": "Reebok",
          "height": 270,
          "width": 480
        },
        {
          "youtubeId": "KZeSQIpAccU",
          "duration": "PT1M50S",
          "title": "Upstairs downstairs",
          "height": 270,
          "width": 480
        },
        {
          "youtubeId": "0bfsjIWPj3M",
          "duration": "PT1M40S",
          "title": "Roger Rabbit",
          "height": 270,
          "width": 480
        },
        {
          "youtubeId": "s2SR7_8tjuo",
          "duration": "PT1M47S",
          "title": "Monastery",
          "height": 270,
          "width": 480
        }
      ]
    },
    {
      "title": "Steps - 2",
      "videos": [
        {
          "youtubeId": "vukDRzUXvbw",
          "duration": "PT1M28S",
          "title": "Kriss Kross",
          "height": 270,
          "width": 480
        },
        {
          "youtubeId": "TgE-tw86f4g",
          "duration": "PT2M17S",
          "title": "Harlem shake",
          "height": 270,
          "width": 480
        },
        {
          "youtubeId": "gNiQfVFuNKM",
          "duration": "PT1M24S",
          "title": "Party machine",
          "height": 270,
          "width": 480
        },
        {
          "youtubeId": "z6mvx6u6t9c",
          "duration": "PT1M36S",
          "title": "Bart Simpson",
          "height": 270,
          "width": 480
        },
        {
          "youtubeId": "p_MY7LlS8c4",
          "duration": "PT2M13S",
          "title": "Bounce",
          "height": 270,
          "width": 480
        }
      ]
    },
    {
      "title": "Steps - 3",
      "videos": [
        {
          "youtubeId": "vD4Mhf8nbKg",
          "duration": "PT1M42S",
          "title": "Wop",
          "height": 270,
          "width": 480
        },
        {
          "youtubeId": "Zo05IfWAoik",
          "duration": "PT1M44S",
          "title": "Bankhead bounce",
          "height": 270,
          "width": 480
        },
        {
          "youtubeId": "PcA-RgveDFs",
          "duration": "PT2M2S",
          "title": "ATL Stomp",
          "height": 270,
          "width": 480
        },
        {
          "youtubeId": "xwNx1c61X_M",
          "duration": "PT2M19S",
          "title": "Cabbage patch",
          "height": 270,
          "width": 480
        },
        {
          "youtubeId": "eyy8QT5lyms",
          "duration": "PT2M2S",
          "title": "Steve Martin",
          "height": 270,
          "width": 480
        }
      ]
    },
    {
      "title": "Final",
      "videos": [
        {
          "youtubeId": "FpwPIXAEzfI",
          "duration": "PT3M1S",
          "title": "Demostración final",
          "height": 270,
          "width": 480
        }
      ]
    }
  ]
}